rankedpairsvoting/__init__.py
rankedpairsvoting/main.py
rankedpairsvoting/objects.py
rankedpairsvoting-0.0.2.dist-info/licenses/LICENSE
rankedpairsvoting-0.0.2.dist-info/METADATA
rankedpairsvoting-0.0.2.dist-info/WHEEL
rankedpairsvoting-0.0.2.dist-info/top_level.txt
rankedpairsvoting-0.0.2.dist-info/RECORD
