Metadata-Version: 2.4
Name: rankedpairsvoting
Version: 0.0.2
Summary: A Python implementation of the Ranked Pairs voting method (Tideman's method)
Author-email: Daniel Navarro Puche <daniel.np.contact+gh@gmail.com>
License-Expression: MIT
Project-URL: Homepage, https://github.com/hakai-vulpes/ranked-pairs-voting
Project-URL: Documentation, https://github.com/hakai-vulpes/ranked-pairs-voting/blob/main/README.md
Project-URL: Repository, https://github.com/hakai-vulpes/ranked-pairs-voting.git
Project-URL: Issues, https://github.com/hakai-vulpes/ranked-pairs-voting/issues
Project-URL: Changelog, https://github.com/hakai-vulpes/ranked-pairs-voting/blob/main/CHANGELOG.md
Keywords: voting,election,condorcet,ranked-pairs,tideman,social-choice
Classifier: Development Status :: 4 - Beta
Classifier: Intended Audience :: Developers
Classifier: Intended Audience :: Science/Research
Classifier: Operating System :: OS Independent
Classifier: Programming Language :: Python :: 3
Classifier: Programming Language :: Python :: 3.9
Classifier: Programming Language :: Python :: 3.10
Classifier: Programming Language :: Python :: 3.11
Classifier: Programming Language :: Python :: 3.12
Classifier: Topic :: Scientific/Engineering :: Mathematics
Classifier: Topic :: Software Development :: Libraries :: Python Modules
Classifier: Typing :: Typed
Requires-Python: >=3.9
License-File: LICENSE
Provides-Extra: dev
Requires-Dist: pytest>=7.0; extra == "dev"
Requires-Dist: pytest-cov>=4.0; extra == "dev"
Requires-Dist: black>=23.0; extra == "dev"
Requires-Dist: flake8>=6.0; extra == "dev"
Requires-Dist: mypy>=1.0; extra == "dev"
Provides-Extra: docs
Requires-Dist: sphinx>=5.0; extra == "docs"
Requires-Dist: sphinx-rtd-theme>=1.0; extra == "docs"
Dynamic: license-file
